envidia/__init__.py
envidia/__main__.py
envidia/core/__init__.py
envidia/core/cli.py
envidia/core/loader.py
envidia-0.1.3.dist-info/licenses/LICENSE
envidia-0.1.3.dist-info/METADATA
envidia-0.1.3.dist-info/WHEEL
envidia-0.1.3.dist-info/entry_points.txt
envidia-0.1.3.dist-info/top_level.txt
envidia-0.1.3.dist-info/RECORD
