Metadata-Version: 2.4
Name: envidia
Version: 0.1.3
Summary: Project level environment variable management utility.
Author-email: Your Name <your.email@example.com>
License: MIT
Project-URL: Homepage, https://github.com/luocfprime/envidia
Project-URL: Repository, https://github.com/luocfprime/envidia.git
Classifier: Intended Audience :: Science/Research
Classifier: License :: OSI Approved :: MIT License
Classifier: Operating System :: OS Independent
Classifier: Topic :: Utilities
Classifier: Programming Language :: Python :: 3
Classifier: Programming Language :: Python :: 3.9
Classifier: Programming Language :: Python :: 3.10
Classifier: Programming Language :: Python :: 3.11
Classifier: Programming Language :: Python :: 3.12
Classifier: Programming Language :: Python :: 3.13
Requires-Python: <4.0,>=3.9
License-File: LICENSE
Requires-Dist: click<9.0.0,>=8.1.8
Requires-Dist: natsort<9.0.0,>=8.4.0
Requires-Dist: cookiecutter<3.0.0,>=2.6.0
Requires-Dist: python-dotenv<2.0.0,>=1.1.1
Provides-Extra: dev
Requires-Dist: pytest<9.0.0,>=8.0.0; extra == "dev"
Requires-Dist: pytest-cov<7.0.0,>=5.0.0; extra == "dev"
Requires-Dist: pytest-mock<4.0.0,>=3.14.0; extra == "dev"
Requires-Dist: black<26.0.0,>=24.0.0; extra == "dev"
Requires-Dist: isort<7.0.0,>=5.13.0; extra == "dev"
Requires-Dist: mypy<2.0.0,>=1.14.0; extra == "dev"
Requires-Dist: flake8<8.0.0,>=7.0.0; extra == "dev"
Requires-Dist: pre-commit<5.0.0,>=3.0.0; extra == "dev"
Requires-Dist: tox<4.29.0,>=4.24.0; extra == "dev"
Dynamic: license-file
